README.md
setup.py
src/__init__.py
src/app/Vinted.py
src/app/__init__.py
src/app/api/__init__.py
src/app/api/brand.py
src/app/api/items.py
src/app/api/shipping_details.py
src/app/api/users.py
src/app/config/__init__.py
src/app/tests/__init__.py
src/app/tests/brands/__init__.py
src/app/tests/brands/test_get_all_brands.py
src/app/tests/brands/test_get_brand.py
src/app/tests/items/__init__.py
src/app/tests/items/test_get_item_details.py
src/app/tests/items/test_get_shipping_details.py
src/app/tests/items/test_search_items.py
src/app/tests/items/test_similar_items.py
src/app/tests/users/__init__.py
src/app/tests/users/test_get_user_info.py
src/app/tests/users/test_get_user_reviews.py
src/app/utils/__init__.py
src/app/utils/config_functions.py
src/app/utils/cookies.py
vinted_api_python.egg-info/PKG-INFO
vinted_api_python.egg-info/SOURCES.txt
vinted_api_python.egg-info/dependency_links.txt
vinted_api_python.egg-info/requires.txt
vinted_api_python.egg-info/top_level.txt