Metadata-Version: 2.1
Name: vinted_api_python
Version: 0.0.2
Summary: A vinted api wrapper in python.
Author: Archithebald
Author-email: <archithebald@proton.me>
Keywords: python,vinted,pypi,api,wrapper
Requires-Dist: requests
Requires-Dist: selenium
